Metadata-Version: 2.1
Name: django-oscar
Version: 3.2.6
Summary: A domain-driven e-commerce framework for Django
Home-page: https://github.com/django-oscar/django-oscar
Author: David Winterbottom
Author-email: david.winterbottom@gmail.com
License: BSD
Keywords: E-commerce,Django,domain-driven
Platform: linux
Classifier: Development Status :: 5 - Production/Stable
Classifier: Environment :: Web Environment
Classifier: Framework :: Django
Classifier: Framework :: Django :: 3.2
Classifier: Framework :: Django :: 4.0
Classifier: Framework :: Django :: 4.1
Classifier: Framework :: Django :: 4.2
Classifier: Intended Audience :: Developers
Classifier: License :: OSI Approved :: BSD License
Classifier: Operating System :: Unix
Classifier: Programming Language :: Python
Classifier: Programming Language :: Python :: 3
Classifier: Programming Language :: Python :: 3.8
Classifier: Programming Language :: Python :: 3.9
Classifier: Programming Language :: Python :: 3.10
Classifier: Programming Language :: Python :: 3.11
Classifier: Topic :: Software Development :: Libraries :: Application Frameworks
Requires-Python: >=3.8
License-File: LICENSE
License-File: AUTHORS
Requires-Dist: setuptools>=51.3.3
Requires-Dist: django<4.3,>=3.2
Requires-Dist: pillow>=6.0
Requires-Dist: django-extra-views<0.15,>=0.13
Requires-Dist: django-haystack>=3.0b1
Requires-Dist: django-treebeard>=4.3.0
Requires-Dist: Babel<3.0,>=1.0
Requires-Dist: purl>=0.7
Requires-Dist: phonenumbers
Requires-Dist: django-phonenumber-field<7.0.0,>=4.0.0
Requires-Dist: factory-boy<3.3,>=3.0
Requires-Dist: django-tables2<=2.7,>=2.3
Requires-Dist: django-widget-tweaks>=1.4.1
Provides-Extra: docs
Requires-Dist: Sphinx>=5.0; extra == "docs"
Requires-Dist: sphinxcontrib-spelling==7.5.1; extra == "docs"
Requires-Dist: sphinx_rtd_theme==1.0.0; extra == "docs"
Requires-Dist: sphinx-issues==3.0.1; extra == "docs"
Requires-Dist: sorl-thumbnail<12.10,>=12.9; extra == "docs"
Requires-Dist: easy-thumbnails<2.8.6,>=2.7; extra == "docs"
Provides-Extra: test
Requires-Dist: WebTest<2.1,>=2.0; extra == "test"
Requires-Dist: coverage<5.5,>=5.4; extra == "test"
Requires-Dist: django-webtest<1.10,>=1.9; extra == "test"
Requires-Dist: psycopg2-binary<2.10,>=2.8; extra == "test"
Requires-Dist: pytest-django<3.9,>=3.7; extra == "test"
Requires-Dist: pytest-xdist<3,>=2.2; extra == "test"
Requires-Dist: tox<4,>=3.21; extra == "test"
Requires-Dist: freezegun<2,>=1.1; extra == "test"
Requires-Dist: pytz; extra == "test"
Requires-Dist: vdt.versionplugin.wheel; extra == "test"
Requires-Dist: sorl-thumbnail<12.10,>=12.9; extra == "test"
Requires-Dist: easy-thumbnails<2.8.6,>=2.7; extra == "test"
Provides-Extra: sorl-thumbnail
Requires-Dist: sorl-thumbnail<12.10,>=12.9; extra == "sorl-thumbnail"
Provides-Extra: easy-thumbnails
Requires-Dist: easy-thumbnails<2.8.6,>=2.7; extra == "easy-thumbnails"
